hscloud/__init__.py
hscloud/client.py
hscloud/const.py
hscloud/helpers.py
hscloud/hscloudexception.py
hscloud-1.0.62.dist-info/licenses/LICENSE
hscloud-1.0.62.dist-info/METADATA
hscloud-1.0.62.dist-info/WHEEL
hscloud-1.0.62.dist-info/entry_points.txt
hscloud-1.0.62.dist-info/top_level.txt
hscloud-1.0.62.dist-info/RECORD
