Metadata-Version: 2.4
Name: hscloud
Version: 1.0.62
Summary: Library to login to Dreo cloud and get device info.
Home-page: https://github.com/dreo-team/hscloud
Download-URL: https://github.com/dreo-team/hscloud/archive/refs/tags/1.0.62.tar.gz
Author: Kane Wang
Author-email: app@hesung.com
License: MIT
License-File: LICENSE
Requires-Dist: requests
Requires-Dist: tzlocal
Requires-Dist: click
Requires-Dist: pycryptodome
Dynamic: author
Dynamic: author-email
Dynamic: download-url
Dynamic: home-page
Dynamic: license
Dynamic: license-file
Dynamic: requires-dist
Dynamic: summary
